{"1":{"id":1,"Name":"\u666E\u901A\u63A8\u8F66","Describe":"\u53EA\u80FD\u643A\u5E26\u62D6\u628A\uFF0C\u6548\u7387\u6781\u4F4E","updateCostCoin":3000,"repair_time":-1},"2":{"id":2,"Name":"\u4FBF\u6377\u63A8\u8F66","Describe":"\u591A\u4E86\u4E00\u4E2A\u69FD\u4F4D\uFF0C\u867D\u7136\u8FD8\u662F\u4E0D\u591F\u7528\uFF0C\u4F46\u6BD4\u6CA1\u6709\u8981\u5F3A","updateCostCoin":50000,"repair_time":-4},"3":{"id":3,"Name":"\u591A\u529F\u80FD\u63A8\u8F66","Describe":"\u55EF~\u8FD9\u63A8\u8F66\u5C31\u6709\u70B9\u50CF\u6837\u4E86","updateCostCoin":300000,"repair_time":-7},"4":{"id":4,"Name":"\u9AD8\u7EA7\u63A8\u8F66","Describe":"\u6700\u597D\u7684\u63A8\u8F66\uFF0C\u610F\u5473\u7740\u6700\u9AD8\u7684\u6548\u7387","updateCostCoin":600000,"repair_time":-10}}